tobii_gaze_server/__init__.py
tobii_gaze_server/__main__.py
tobii_gaze_server/py.typed
tobii_gaze_server/server.py
tobii_gaze_server-0.1.0.dist-info/licenses/LICENSE
tobii_gaze_server-0.1.0.dist-info/METADATA
tobii_gaze_server-0.1.0.dist-info/WHEEL
tobii_gaze_server-0.1.0.dist-info/entry_points.txt
tobii_gaze_server-0.1.0.dist-info/top_level.txt
tobii_gaze_server-0.1.0.dist-info/RECORD
