Metadata-Version: 2.4
Name: tobii-gaze-server
Version: 0.1.0
Summary: WebSocket server for Tobii Eye Tracker gaze data using Tobii Stream Engine
Author: Thomas Wagner
License: MIT
Project-URL: Homepage, https://github.com/yourusername/tobii-gaze-server
Project-URL: Repository, https://github.com/yourusername/tobii-gaze-server
Project-URL: Issues, https://github.com/yourusername/tobii-gaze-server/issues
Keywords: tobii,eye-tracking,gaze,websocket,stream-engine
Classifier: Development Status :: 4 - Beta
Classifier: Intended Audience :: Developers
Classifier: License :: OSI Approved :: MIT License
Classifier: Operating System :: Microsoft :: Windows
Classifier: Programming Language :: Python :: 3
Classifier: Programming Language :: Python :: 3.8
Classifier: Programming Language :: Python :: 3.9
Classifier: Programming Language :: Python :: 3.10
Classifier: Programming Language :: Python :: 3.11
Classifier: Programming Language :: Python :: 3.12
Classifier: Topic :: Scientific/Engineering :: Human Machine Interfaces
Requires-Python: >=3.8
License-File: LICENSE
Requires-Dist: websockets>=10.0
Provides-Extra: demo
Requires-Dist: pygame>=2.0; extra == "demo"
Provides-Extra: dev
Requires-Dist: pytest>=7.0; extra == "dev"
Requires-Dist: build; extra == "dev"
Requires-Dist: twine; extra == "dev"
Requires-Dist: pygame>=2.0; extra == "dev"
Dynamic: license-file
